pygarmin/__init__.py
pygarmin/capabilities.py
pygarmin/datatype.py
pygarmin/error.py
pygarmin/fit.py
pygarmin/garmin.py
pygarmin/gpsd.py
pygarmin/gpx.py
pygarmin/link.py
pygarmin/logger.py
pygarmin/protocol.py
pygarmin/pygarmin.py
pygarmin-2.0.3.dist-info/LICENSE
pygarmin-2.0.3.dist-info/METADATA
pygarmin-2.0.3.dist-info/WHEEL
pygarmin-2.0.3.dist-info/entry_points.txt
pygarmin-2.0.3.dist-info/top_level.txt
pygarmin-2.0.3.dist-info/RECORD
