Metadata-Version: 2.1
Name: pygarmin
Version: 2.0.3
Summary: A Python interface to older Garmin GPS equipment
Home-page: http://github.com/quentinsf/pygarmin
Author: Folkert van der Beek
License: GNU General Public License version 2 or any later version
Project-URL: Homepage, https://github.com/quentinsf/pygarmin
Project-URL: Bug Tracker, https://github.com/quentinsf/pygarmin/issues
Keywords: garmin,gps
Classifier: Development Status :: 5 - Production/Stable
Classifier: License :: OSI Approved :: GNU General Public License v2 or later (GPLv2+)
Classifier: Operating System :: OS Independent
Classifier: Programming Language :: Python :: 3
Classifier: Programming Language :: Python :: 3.9
Classifier: Programming Language :: Python :: 3.10
Classifier: Programming Language :: Python :: 3.11
Classifier: Programming Language :: Python :: 3.12
Classifier: Topic :: Scientific/Engineering :: GIS
Classifier: Topic :: Software Development :: Libraries :: Python Modules
Classifier: Topic :: System :: Hardware :: Hardware Drivers
Classifier: Topic :: Utilities
Requires-Python: >=3.9
License-File: LICENSE
Requires-Dist: fit-tool>=0.9.13
Requires-Dist: gpxpy>=1.5.0
Requires-Dist: microbmp>=0.3.0
Requires-Dist: Pillow>=9.3.0
Requires-Dist: pyserial>=3.5
Requires-Dist: pyusb>=1.2.1
Requires-Dist: rawutil>=2.7.4
Requires-Dist: tabulate>=0.9.0
Requires-Dist: tqdm>=4.64.1
